minid/__init__.py
minid/__main__.py
minid/command.py
minid/config.py
minid/db.py
minid/exceptions.py
minid/utils.py
minid_py-0.1.0.dist-info/METADATA
minid_py-0.1.0.dist-info/WHEEL
minid_py-0.1.0.dist-info/entry_points.txt
minid_py-0.1.0.dist-info/RECORD
