Metadata-Version: 2.4
Name: minid-py
Version: 0.1.0
Summary: Jira-like IDs for links and short content.
Requires-Python: >=3.13
Requires-Dist: click>=8.2.1
Requires-Dist: lmdb>=1.6.2
Requires-Dist: rich>=14.0.0
Requires-Dist: urlextract>=1.9.0
